jupdeck/__init__.py
jupdeck/changelog.md
jupdeck/cli.py
jupdeck/core/__init__.py
jupdeck/core/models.py
jupdeck/core/parser.py
jupdeck/core/renderer.py
jupdeck-0.1.1.dist-info/LICENSE
jupdeck-0.1.1.dist-info/METADATA
jupdeck-0.1.1.dist-info/WHEEL
jupdeck-0.1.1.dist-info/entry_points.txt
jupdeck-0.1.1.dist-info/RECORD
