Metadata-Version: 2.3
Name: jupdeck
Version: 0.1.1
Summary: Create Audience-Ready Presentations from Jupyter Notebooks
License: Apache-2.0
Author: Jen Dobson
Author-email: jendobson@gmail.com
Requires-Python: >=3.10,<3.13
Classifier: License :: OSI Approved :: Apache Software License
Classifier: Programming Language :: Python :: 3
Classifier: Programming Language :: Python :: 3.10
Classifier: Programming Language :: Python :: 3.11
Classifier: Programming Language :: Python :: 3.12
Requires-Dist: exceptiongroup (>=1.1.3,<2.0.0) ; python_version < "3.11"
Requires-Dist: ipykernel
Requires-Dist: jupyter_core (>=5.5.0,<6.0.0)
Requires-Dist: matplotlib
Requires-Dist: mistune (>=3.1.3,<4.0.0)
Requires-Dist: nbconvert (>=7.10.0,<8.0.0)
Requires-Dist: nbformat (>=5.9.0,<6.0.0)
Requires-Dist: numpy
Requires-Dist: pandas
Requires-Dist: python-pptx (>=1.0.2,<2.0.0)
Requires-Dist: scikit-learn
Requires-Dist: scipy (>=1.15.3,<2.0.0)
Requires-Dist: seaborn
